[{"code":"LW","display":"Liquid Waste"},{"code":"LI","display":"Measurable Liquid Item"},{"code":"DI","display":"Diluent"},{"code":"SR","display":"Single Test Reagent"},{"code":"SC","display":"Countable Solid Item"},{"code":"RC","display":"Reagent Calibrator"},{"code":"PW","display":"Purified Water"},{"code":"PT","display":"Pretreatment"},{"code":"OT","display":"Other"},{"code":"SW","display":"Solid Waste"},{"code":"MR","display":"Multiple Test Reagent"},{"code":"CO","display":"Control Reagent"}]